Metadata-Version: 1.1
Name: MastodonInstances
Version: 0.3
Summary: Python Interface to instances.social
Home-page: https://github.com/cakeisalie5/MastodonInstances
Author: Thomas "Cakeisalie5" Touhey
Author-email: thomas@touhey.fr
License: UNKNOWN
Keywords: mastodon instances instances.social api microblogging
Platform: UNKNOWN
Classifier: Development Status :: 4 - Beta
Classifier: Intended Audience :: Developers
Classifier: License :: OSI Approved :: MIT License
Classifier: Natural Language :: English
Classifier: Operating System :: OS Independent
Classifier: Programming Language :: Python :: 3
